<?xml version="1.0" encoding="UTF-8"?>
<export version="E">
  <design>
    <source>C:\Work\658-Computer\Kicad\Computer\Computer.kicad_sch</source>
    <date>2022/02/01 19:53:45</date>
    <tool>Eeschema (6.0.1)</tool>
    <sheet number="1" name="/" tstamps="/">
      <title_block>
        <title/>
        <company/>
        <rev/>
        <date/>
        <source>Computer.kicad_sch</source>
        <comment number="1" value=""/>
        <comment number="2" value=""/>
        <comment number="3" value=""/>
        <comment number="4" value=""/>
        <comment number="5" value=""/>
        <comment number="6" value=""/>
        <comment number="7" value=""/>
        <comment number="8" value=""/>
        <comment number="9" value=""/>
      </title_block>
    </sheet>
    <sheet number="2" name="/Timing Circuit/" tstamps="/e95b1d8e-2e4e-4877-9121-2ee2965866b4/">
      <title_block>
        <title/>
        <company/>
        <rev/>
        <date/>
        <source>Timing_Circuit.kicad_sch</source>
        <comment number="1" value=""/>
        <comment number="2" value=""/>
        <comment number="3" value=""/>
        <comment number="4" value=""/>
        <comment number="5" value=""/>
        <comment number="6" value=""/>
        <comment number="7" value=""/>
        <comment number="8" value=""/>
        <comment number="9" value=""/>
      </title_block>
    </sheet>
  </design>
  <components>
    <comp ref="C1">
      <value>CP1000uF</value>
      <footprint>Capacitor_THT:CP_Radial_D7.5mm_P2.50mm</footprint>
      <libsource lib="Device" part="CP" description=""/>
      <property name="Sheetname" value="Timing Circuit"/>
      <property name="Sheetfile" value="Timing_Circuit.kicad_sch"/>
      <sheetpath names="/Timing Circuit/" tstamps="/e95b1d8e-2e4e-4877-9121-2ee2965866b4/"/>
      <tstamps>fb65aa41-1254-461d-87b7-a8b4976bbc20</tstamps>
    </comp>
    <comp ref="C2">
      <value>CP1000uF</value>
      <footprint>Capacitor_THT:CP_Radial_D7.5mm_P2.50mm</footprint>
      <libsource lib="Device" part="CP" description=""/>
      <property name="Sheetname" value="Timing Circuit"/>
      <property name="Sheetfile" value="Timing_Circuit.kicad_sch"/>
      <sheetpath names="/Timing Circuit/" tstamps="/e95b1d8e-2e4e-4877-9121-2ee2965866b4/"/>
      <tstamps>579bbef2-7988-4cd8-84eb-a6f192abafd8</tstamps>
    </comp>
    <comp ref="C3">
      <value>100pF MLCC</value>
      <footprint>CAPC2012X90N</footprint>
      <datasheet>https://katalog.we-online.com/pbs/datasheet/885012207027.pdf</datasheet>
      <fields>
        <field name="Description">Multilayer Ceramic Chip Capacitor WCAP-CSGP Series 0805 100pF X7R0805101K016DFCT10000</field>
        <field name="Height">0.9</field>
        <field name="Manufacturer_Name">Wurth Elektronik</field>
        <field name="Manufacturer_Part_Number">885012207027</field>
        <field name="Mouser Part Number">710-885012207027</field>
        <field name="Mouser Price/Stock">https://www.mouser.co.uk/ProductDetail/Wurth-Elektronik/885012207027?qs=0KOYDY2FL28IWYVDh0DkrQ%3D%3D</field>
      </fields>
      <libsource lib="Wurth_Elektronik" part="885012207027" description="Multilayer Ceramic Chip Capacitor WCAP-CSGP Series 0805 100pF X7R0805101K016DFCT10000"/>
      <property name="Description" value="Multilayer Ceramic Chip Capacitor WCAP-CSGP Series 0805 100pF X7R0805101K016DFCT10000"/>
      <property name="Height" value="0.9"/>
      <property name="Mouser Part Number" value="710-885012207027"/>
      <property name="Mouser Price/Stock" value="https://www.mouser.co.uk/ProductDetail/Wurth-Elektronik/885012207027?qs=0KOYDY2FL28IWYVDh0DkrQ%3D%3D"/>
      <property name="Manufacturer_Name" value="Wurth Elektronik"/>
      <property name="Manufacturer_Part_Number" value="885012207027"/>
      <property name="Sheetname" value="Timing Circuit"/>
      <property name="Sheetfile" value="Timing_Circuit.kicad_sch"/>
      <sheetpath names="/Timing Circuit/" tstamps="/e95b1d8e-2e4e-4877-9121-2ee2965866b4/"/>
      <tstamps>e91c910c-9535-45c8-9b51-9e410e51efd8</tstamps>
    </comp>
    <comp ref="C4">
      <value>1000pF MLCC</value>
      <footprint>CAPC2012X90N</footprint>
      <datasheet>https://katalog.we-online.com/pbs/datasheet/885012207033.pdf</datasheet>
      <fields>
        <field name="Description">Multilayer Ceramic Chip Capacitor WCAP-CSGP Series 0805 1000pF X7R0805102K016DFCT10000</field>
        <field name="Height">0.9</field>
        <field name="Manufacturer_Name">Wurth Elektronik</field>
        <field name="Manufacturer_Part_Number">885012207033</field>
        <field name="Mouser Part Number">710-885012207033</field>
        <field name="Mouser Price/Stock">https://www.mouser.co.uk/ProductDetail/Wurth-Elektronik/885012207033?qs=0KOYDY2FL28ky2lrUPvQ%2Fw%3D%3D</field>
      </fields>
      <libsource lib="Wurth_Elektronik" part="885012207033" description="Multilayer Ceramic Chip Capacitor WCAP-CSGP Series 0805 1000pF X7R0805102K016DFCT10000"/>
      <property name="Description" value="Multilayer Ceramic Chip Capacitor WCAP-CSGP Series 0805 1000pF X7R0805102K016DFCT10000"/>
      <property name="Height" value="0.9"/>
      <property name="Mouser Part Number" value="710-885012207033"/>
      <property name="Mouser Price/Stock" value="https://www.mouser.co.uk/ProductDetail/Wurth-Elektronik/885012207033?qs=0KOYDY2FL28ky2lrUPvQ%2Fw%3D%3D"/>
      <property name="Manufacturer_Name" value="Wurth Elektronik"/>
      <property name="Manufacturer_Part_Number" value="885012207033"/>
      <property name="Sheetname" value="Timing Circuit"/>
      <property name="Sheetfile" value="Timing_Circuit.kicad_sch"/>
      <sheetpath names="/Timing Circuit/" tstamps="/e95b1d8e-2e4e-4877-9121-2ee2965866b4/"/>
      <tstamps>0b620490-6aa9-479c-b3bb-204539a513d4</tstamps>
    </comp>
    <comp ref="C5">
      <value>1000pF MLCC</value>
      <footprint>CAPC2012X90N</footprint>
      <datasheet>https://katalog.we-online.com/pbs/datasheet/885012207033.pdf</datasheet>
      <fields>
        <field name="Description">Multilayer Ceramic Chip Capacitor WCAP-CSGP Series 0805 1000pF X7R0805102K016DFCT10000</field>
        <field name="Height">0.9</field>
        <field name="Manufacturer_Name">Wurth Elektronik</field>
        <field name="Manufacturer_Part_Number">885012207033</field>
        <field name="Mouser Part Number">710-885012207033</field>
        <field name="Mouser Price/Stock">https://www.mouser.co.uk/ProductDetail/Wurth-Elektronik/885012207033?qs=0KOYDY2FL28ky2lrUPvQ%2Fw%3D%3D</field>
      </fields>
      <libsource lib="Wurth_Elektronik" part="885012207033" description="Multilayer Ceramic Chip Capacitor WCAP-CSGP Series 0805 1000pF X7R0805102K016DFCT10000"/>
      <property name="Description" value="Multilayer Ceramic Chip Capacitor WCAP-CSGP Series 0805 1000pF X7R0805102K016DFCT10000"/>
      <property name="Height" value="0.9"/>
      <property name="Mouser Part Number" value="710-885012207033"/>
      <property name="Mouser Price/Stock" value="https://www.mouser.co.uk/ProductDetail/Wurth-Elektronik/885012207033?qs=0KOYDY2FL28ky2lrUPvQ%2Fw%3D%3D"/>
      <property name="Manufacturer_Name" value="Wurth Elektronik"/>
      <property name="Manufacturer_Part_Number" value="885012207033"/>
      <property name="Sheetname" value="Timing Circuit"/>
      <property name="Sheetfile" value="Timing_Circuit.kicad_sch"/>
      <sheetpath names="/Timing Circuit/" tstamps="/e95b1d8e-2e4e-4877-9121-2ee2965866b4/"/>
      <tstamps>572962c1-b707-4e65-8706-eaad4243d397</tstamps>
    </comp>
    <comp ref="C6">
      <value>1000pF MLCC</value>
      <footprint>CAPC2012X90N</footprint>
      <datasheet>https://katalog.we-online.com/pbs/datasheet/885012207033.pdf</datasheet>
      <fields>
        <field name="Description">Multilayer Ceramic Chip Capacitor WCAP-CSGP Series 0805 1000pF X7R0805102K016DFCT10000</field>
        <field name="Height">0.9</field>
        <field name="Manufacturer_Name">Wurth Elektronik</field>
        <field name="Manufacturer_Part_Number">885012207033</field>
        <field name="Mouser Part Number">710-885012207033</field>
        <field name="Mouser Price/Stock">https://www.mouser.co.uk/ProductDetail/Wurth-Elektronik/885012207033?qs=0KOYDY2FL28ky2lrUPvQ%2Fw%3D%3D</field>
      </fields>
      <libsource lib="Wurth_Elektronik" part="885012207033" description="Multilayer Ceramic Chip Capacitor WCAP-CSGP Series 0805 1000pF X7R0805102K016DFCT10000"/>
      <property name="Description" value="Multilayer Ceramic Chip Capacitor WCAP-CSGP Series 0805 1000pF X7R0805102K016DFCT10000"/>
      <property name="Height" value="0.9"/>
      <property name="Mouser Part Number" value="710-885012207033"/>
      <property name="Mouser Price/Stock" value="https://www.mouser.co.uk/ProductDetail/Wurth-Elektronik/885012207033?qs=0KOYDY2FL28ky2lrUPvQ%2Fw%3D%3D"/>
      <property name="Manufacturer_Name" value="Wurth Elektronik"/>
      <property name="Manufacturer_Part_Number" value="885012207033"/>
      <property name="Sheetname" value="Timing Circuit"/>
      <property name="Sheetfile" value="Timing_Circuit.kicad_sch"/>
      <sheetpath names="/Timing Circuit/" tstamps="/e95b1d8e-2e4e-4877-9121-2ee2965866b4/"/>
      <tstamps>3fd68bf1-bb7e-4d8f-9d2a-0ffd5536558f</tstamps>
    </comp>
    <comp ref="C7">
      <value>1000pF MLCC</value>
      <footprint>CAPC2012X90N</footprint>
      <datasheet>https://katalog.we-online.com/pbs/datasheet/885012207033.pdf</datasheet>
      <fields>
        <field name="Description">Multilayer Ceramic Chip Capacitor WCAP-CSGP Series 0805 1000pF X7R0805102K016DFCT10000</field>
        <field name="Height">0.9</field>
        <field name="Manufacturer_Name">Wurth Elektronik</field>
        <field name="Manufacturer_Part_Number">885012207033</field>
        <field name="Mouser Part Number">710-885012207033</field>
        <field name="Mouser Price/Stock">https://www.mouser.co.uk/ProductDetail/Wurth-Elektronik/885012207033?qs=0KOYDY2FL28ky2lrUPvQ%2Fw%3D%3D</field>
      </fields>
      <libsource lib="Wurth_Elektronik" part="885012207033" description="Multilayer Ceramic Chip Capacitor WCAP-CSGP Series 0805 1000pF X7R0805102K016DFCT10000"/>
      <property name="Description" value="Multilayer Ceramic Chip Capacitor WCAP-CSGP Series 0805 1000pF X7R0805102K016DFCT10000"/>
      <property name="Height" value="0.9"/>
      <property name="Mouser Part Number" value="710-885012207033"/>
      <property name="Mouser Price/Stock" value="https://www.mouser.co.uk/ProductDetail/Wurth-Elektronik/885012207033?qs=0KOYDY2FL28ky2lrUPvQ%2Fw%3D%3D"/>
      <property name="Manufacturer_Name" value="Wurth Elektronik"/>
      <property name="Manufacturer_Part_Number" value="885012207033"/>
      <property name="Sheetname" value="Timing Circuit"/>
      <property name="Sheetfile" value="Timing_Circuit.kicad_sch"/>
      <sheetpath names="/Timing Circuit/" tstamps="/e95b1d8e-2e4e-4877-9121-2ee2965866b4/"/>
      <tstamps>bf948544-1a34-4457-91c4-a49453889f09</tstamps>
    </comp>
    <comp ref="C8">
      <value>1000pF MLCC</value>
      <footprint>CAPC2012X90N</footprint>
      <datasheet>https://katalog.we-online.com/pbs/datasheet/885012207033.pdf</datasheet>
      <fields>
        <field name="Description">Multilayer Ceramic Chip Capacitor WCAP-CSGP Series 0805 1000pF X7R0805102K016DFCT10000</field>
        <field name="Height">0.9</field>
        <field name="Manufacturer_Name">Wurth Elektronik</field>
        <field name="Manufacturer_Part_Number">885012207033</field>
        <field name="Mouser Part Number">710-885012207033</field>
        <field name="Mouser Price/Stock">https://www.mouser.co.uk/ProductDetail/Wurth-Elektronik/885012207033?qs=0KOYDY2FL28ky2lrUPvQ%2Fw%3D%3D</field>
      </fields>
      <libsource lib="Wurth_Elektronik" part="885012207033" description="Multilayer Ceramic Chip Capacitor WCAP-CSGP Series 0805 1000pF X7R0805102K016DFCT10000"/>
      <property name="Description" value="Multilayer Ceramic Chip Capacitor WCAP-CSGP Series 0805 1000pF X7R0805102K016DFCT10000"/>
      <property name="Height" value="0.9"/>
      <property name="Mouser Part Number" value="710-885012207033"/>
      <property name="Mouser Price/Stock" value="https://www.mouser.co.uk/ProductDetail/Wurth-Elektronik/885012207033?qs=0KOYDY2FL28ky2lrUPvQ%2Fw%3D%3D"/>
      <property name="Manufacturer_Name" value="Wurth Elektronik"/>
      <property name="Manufacturer_Part_Number" value="885012207033"/>
      <property name="Sheetname" value="Timing Circuit"/>
      <property name="Sheetfile" value="Timing_Circuit.kicad_sch"/>
      <sheetpath names="/Timing Circuit/" tstamps="/e95b1d8e-2e4e-4877-9121-2ee2965866b4/"/>
      <tstamps>2f12aea5-61c1-4447-9a87-f24065546d16</tstamps>
    </comp>
    <comp ref="C9">
      <value>1000pF MLCC</value>
      <footprint>CAPC2012X90N</footprint>
      <datasheet>https://katalog.we-online.com/pbs/datasheet/885012207033.pdf</datasheet>
      <fields>
        <field name="Description">Multilayer Ceramic Chip Capacitor WCAP-CSGP Series 0805 1000pF X7R0805102K016DFCT10000</field>
        <field name="Height">0.9</field>
        <field name="Manufacturer_Name">Wurth Elektronik</field>
        <field name="Manufacturer_Part_Number">885012207033</field>
        <field name="Mouser Part Number">710-885012207033</field>
        <field name="Mouser Price/Stock">https://www.mouser.co.uk/ProductDetail/Wurth-Elektronik/885012207033?qs=0KOYDY2FL28ky2lrUPvQ%2Fw%3D%3D</field>
      </fields>
      <libsource lib="Wurth_Elektronik" part="885012207033" description="Multilayer Ceramic Chip Capacitor WCAP-CSGP Series 0805 1000pF X7R0805102K016DFCT10000"/>
      <property name="Description" value="Multilayer Ceramic Chip Capacitor WCAP-CSGP Series 0805 1000pF X7R0805102K016DFCT10000"/>
      <property name="Height" value="0.9"/>
      <property name="Mouser Part Number" value="710-885012207033"/>
      <property name="Mouser Price/Stock" value="https://www.mouser.co.uk/ProductDetail/Wurth-Elektronik/885012207033?qs=0KOYDY2FL28ky2lrUPvQ%2Fw%3D%3D"/>
      <property name="Manufacturer_Name" value="Wurth Elektronik"/>
      <property name="Manufacturer_Part_Number" value="885012207033"/>
      <property name="Sheetname" value="Timing Circuit"/>
      <property name="Sheetfile" value="Timing_Circuit.kicad_sch"/>
      <sheetpath names="/Timing Circuit/" tstamps="/e95b1d8e-2e4e-4877-9121-2ee2965866b4/"/>
      <tstamps>fd7ee685-071d-4d0e-ad17-7c6eea25db66</tstamps>
    </comp>
    <comp ref="C10">
      <value>1000pF MLCC</value>
      <footprint>CAPC2012X90N</footprint>
      <datasheet>https://katalog.we-online.com/pbs/datasheet/885012207033.pdf</datasheet>
      <fields>
        <field name="Description">Multilayer Ceramic Chip Capacitor WCAP-CSGP Series 0805 1000pF X7R0805102K016DFCT10000</field>
        <field name="Height">0.9</field>
        <field name="Manufacturer_Name">Wurth Elektronik</field>
        <field name="Manufacturer_Part_Number">885012207033</field>
        <field name="Mouser Part Number">710-885012207033</field>
        <field name="Mouser Price/Stock">https://www.mouser.co.uk/ProductDetail/Wurth-Elektronik/885012207033?qs=0KOYDY2FL28ky2lrUPvQ%2Fw%3D%3D</field>
      </fields>
      <libsource lib="Wurth_Elektronik" part="885012207033" description="Multilayer Ceramic Chip Capacitor WCAP-CSGP Series 0805 1000pF X7R0805102K016DFCT10000"/>
      <property name="Description" value="Multilayer Ceramic Chip Capacitor WCAP-CSGP Series 0805 1000pF X7R0805102K016DFCT10000"/>
      <property name="Height" value="0.9"/>
      <property name="Mouser Part Number" value="710-885012207033"/>
      <property name="Mouser Price/Stock" value="https://www.mouser.co.uk/ProductDetail/Wurth-Elektronik/885012207033?qs=0KOYDY2FL28ky2lrUPvQ%2Fw%3D%3D"/>
      <property name="Manufacturer_Name" value="Wurth Elektronik"/>
      <property name="Manufacturer_Part_Number" value="885012207033"/>
      <property name="Sheetname" value="Timing Circuit"/>
      <property name="Sheetfile" value="Timing_Circuit.kicad_sch"/>
      <sheetpath names="/Timing Circuit/" tstamps="/e95b1d8e-2e4e-4877-9121-2ee2965866b4/"/>
      <tstamps>12bf76fa-295b-4861-8f4d-c0a9cbf40ca0</tstamps>
    </comp>
    <comp ref="C11">
      <value>1000pF MLCC</value>
      <footprint>CAPC2012X90N</footprint>
      <datasheet>https://katalog.we-online.com/pbs/datasheet/885012207033.pdf</datasheet>
      <fields>
        <field name="Description">Multilayer Ceramic Chip Capacitor WCAP-CSGP Series 0805 1000pF X7R0805102K016DFCT10000</field>
        <field name="Height">0.9</field>
        <field name="Manufacturer_Name">Wurth Elektronik</field>
        <field name="Manufacturer_Part_Number">885012207033</field>
        <field name="Mouser Part Number">710-885012207033</field>
        <field name="Mouser Price/Stock">https://www.mouser.co.uk/ProductDetail/Wurth-Elektronik/885012207033?qs=0KOYDY2FL28ky2lrUPvQ%2Fw%3D%3D</field>
      </fields>
      <libsource lib="Wurth_Elektronik" part="885012207033" description="Multilayer Ceramic Chip Capacitor WCAP-CSGP Series 0805 1000pF X7R0805102K016DFCT10000"/>
      <property name="Description" value="Multilayer Ceramic Chip Capacitor WCAP-CSGP Series 0805 1000pF X7R0805102K016DFCT10000"/>
      <property name="Height" value="0.9"/>
      <property name="Mouser Part Number" value="710-885012207033"/>
      <property name="Mouser Price/Stock" value="https://www.mouser.co.uk/ProductDetail/Wurth-Elektronik/885012207033?qs=0KOYDY2FL28ky2lrUPvQ%2Fw%3D%3D"/>
      <property name="Manufacturer_Name" value="Wurth Elektronik"/>
      <property name="Manufacturer_Part_Number" value="885012207033"/>
      <property name="Sheetname" value="Timing Circuit"/>
      <property name="Sheetfile" value="Timing_Circuit.kicad_sch"/>
      <sheetpath names="/Timing Circuit/" tstamps="/e95b1d8e-2e4e-4877-9121-2ee2965866b4/"/>
      <tstamps>5e47c4c8-6146-4197-babb-8fe54fd71416</tstamps>
    </comp>
    <comp ref="C12">
      <value>100pF MLCC</value>
      <footprint>CAPC2012X90N</footprint>
      <datasheet>https://katalog.we-online.com/pbs/datasheet/885012207027.pdf</datasheet>
      <fields>
        <field name="Description">Multilayer Ceramic Chip Capacitor WCAP-CSGP Series 0805 100pF X7R0805101K016DFCT10000</field>
        <field name="Height">0.9</field>
        <field name="Manufacturer_Name">Wurth Elektronik</field>
        <field name="Manufacturer_Part_Number">885012207027</field>
        <field name="Mouser Part Number">710-885012207027</field>
        <field name="Mouser Price/Stock">https://www.mouser.co.uk/ProductDetail/Wurth-Elektronik/885012207027?qs=0KOYDY2FL28IWYVDh0DkrQ%3D%3D</field>
      </fields>
      <libsource lib="Wurth_Elektronik" part="885012207027" description="Multilayer Ceramic Chip Capacitor WCAP-CSGP Series 0805 100pF X7R0805101K016DFCT10000"/>
      <property name="Description" value="Multilayer Ceramic Chip Capacitor WCAP-CSGP Series 0805 100pF X7R0805101K016DFCT10000"/>
      <property name="Height" value="0.9"/>
      <property name="Mouser Part Number" value="710-885012207027"/>
      <property name="Mouser Price/Stock" value="https://www.mouser.co.uk/ProductDetail/Wurth-Elektronik/885012207027?qs=0KOYDY2FL28IWYVDh0DkrQ%3D%3D"/>
      <property name="Manufacturer_Name" value="Wurth Elektronik"/>
      <property name="Manufacturer_Part_Number" value="885012207027"/>
      <property name="Sheetname" value="Timing Circuit"/>
      <property name="Sheetfile" value="Timing_Circuit.kicad_sch"/>
      <sheetpath names="/Timing Circuit/" tstamps="/e95b1d8e-2e4e-4877-9121-2ee2965866b4/"/>
      <tstamps>21dd33b9-70cb-45e8-9c71-d3b12b9e5874</tstamps>
    </comp>
    <comp ref="IC1">
      <value>DS1813R</value>
      <footprint>SOT95P237X112-3N</footprint>
      <datasheet>https://componentsearchengine.com/Datasheets/2/DS1813R-10+T&amp;R.pdf</datasheet>
      <fields>
        <field name="Description">Maxim DS1813R-10+T&amp;R, Voltage Supervisor 4.25  4.49 V, Reset Input, 3-Pin SOT-23</field>
        <field name="Height">1.12</field>
        <field name="Manufacturer_Name">Maxim Integrated</field>
        <field name="Manufacturer_Part_Number">DS1813R-10+T&amp;R</field>
        <field name="Mouser Part Number">700-DS1813R-10T&amp;R</field>
        <field name="Mouser Price/Stock">https://www.mouser.co.uk/ProductDetail/Maxim-Integrated/DS1813R-10%2bTR?qs=0Y9aZN%252BMVCUEX%2FgvPX%252B6Nw%3D%3D</field>
      </fields>
      <libsource lib="Maxim" part="DS1813R-10+T&amp;R" description="Maxim DS1813R-10+T&amp;R, Voltage Supervisor 4.25  4.49 V, Reset Input, 3-Pin SOT-23"/>
      <property name="Description" value="Maxim DS1813R-10+T&amp;R, Voltage Supervisor 4.25  4.49 V, Reset Input, 3-Pin SOT-23"/>
      <property name="Height" value="1.12"/>
      <property name="Mouser Part Number" value="700-DS1813R-10T&amp;R"/>
      <property name="Mouser Price/Stock" value="https://www.mouser.co.uk/ProductDetail/Maxim-Integrated/DS1813R-10%2bTR?qs=0Y9aZN%252BMVCUEX%2FgvPX%252B6Nw%3D%3D"/>
      <property name="Manufacturer_Name" value="Maxim Integrated"/>
      <property name="Manufacturer_Part_Number" value="DS1813R-10+T&amp;R"/>
      <property name="Sheetname" value="Timing Circuit"/>
      <property name="Sheetfile" value="Timing_Circuit.kicad_sch"/>
      <sheetpath names="/Timing Circuit/" tstamps="/e95b1d8e-2e4e-4877-9121-2ee2965866b4/"/>
      <tstamps>973569f8-1b57-4710-8bae-c3fabf3b78f3</tstamps>
    </comp>
    <comp ref="IC2">
      <value>LVC74</value>
      <footprint>SOP65P640X110-14N</footprint>
      <datasheet>https://assets.nexperia.com/documents/data-sheet/74LVC74A.pdf</datasheet>
      <fields>
        <field name="Description">74LVC74A - Dual D-type flip-flop with set and reset; positive-edge trigger@en-us</field>
        <field name="Height">1.1</field>
        <field name="Manufacturer_Name">Nexperia</field>
        <field name="Manufacturer_Part_Number">74LVC74APW,118</field>
        <field name="Mouser Part Number">771-74LVC74APW-T</field>
        <field name="Mouser Price/Stock">https://www.mouser.co.uk/ProductDetail/Nexperia/74LVC74APW118?qs=me8TqzrmIYVtXwVfet0lzw%3D%3D</field>
      </fields>
      <libsource lib="Nexperia" part="74LVC74APW,118" description="74LVC74A - Dual D-type flip-flop with set and reset; positive-edge trigger@en-us"/>
      <property name="Description" value="74LVC74A - Dual D-type flip-flop with set and reset; positive-edge trigger@en-us"/>
      <property name="Height" value="1.1"/>
      <property name="Mouser Part Number" value="771-74LVC74APW-T"/>
      <property name="Mouser Price/Stock" value="https://www.mouser.co.uk/ProductDetail/Nexperia/74LVC74APW118?qs=me8TqzrmIYVtXwVfet0lzw%3D%3D"/>
      <property name="Manufacturer_Name" value="Nexperia"/>
      <property name="Manufacturer_Part_Number" value="74LVC74APW,118"/>
      <property name="Sheetname" value="Timing Circuit"/>
      <property name="Sheetfile" value="Timing_Circuit.kicad_sch"/>
      <sheetpath names="/Timing Circuit/" tstamps="/e95b1d8e-2e4e-4877-9121-2ee2965866b4/"/>
      <tstamps>7e2866f0-de1e-4b92-95e2-02bc3f3893f0</tstamps>
    </comp>
    <comp ref="IC3">
      <value>LVC2G04</value>
      <footprint>SOP65P210X110-6N</footprint>
      <datasheet>https://assets.nexperia.com/documents/data-sheet/74LVC2G04_Q100.pdf</datasheet>
      <fields>
        <field name="Arrow Part Number">74LVC2G04GW-Q100H</field>
        <field name="Arrow Price/Stock">https://www.arrow.com/en/products/74lvc2g04gw-q100h/nexperia</field>
        <field name="Description">74LVC2G04-Q100 - Dual inverter@en-us</field>
        <field name="Height">1.1</field>
        <field name="Manufacturer_Name">Nexperia</field>
        <field name="Manufacturer_Part_Number">74LVC2G04GW-Q100H</field>
        <field name="Mouser Part Number">771-74LVC2G04GWQ100H</field>
        <field name="Mouser Price/Stock">https://www.mouser.co.uk/ProductDetail/Nexperia/74LVC2G04GW-Q100H?qs=Yna0arPQ0CQTXbBDVSrZqQ%3D%3D</field>
      </fields>
      <libsource lib="Nexperia" part="74LVC2G04GW-Q100H" description=""/>
      <property name="Description" value="74LVC2G04-Q100 - Dual inverter@en-us"/>
      <property name="Height" value="1.1"/>
      <property name="Manufacturer_Name" value="Nexperia"/>
      <property name="Manufacturer_Part_Number" value="74LVC2G04GW-Q100H"/>
      <property name="Mouser Part Number" value="771-74LVC2G04GWQ100H"/>
      <property name="Mouser Price/Stock" value="https://www.mouser.co.uk/ProductDetail/Nexperia/74LVC2G04GW-Q100H?qs=Yna0arPQ0CQTXbBDVSrZqQ%3D%3D"/>
      <property name="Arrow Part Number" value="74LVC2G04GW-Q100H"/>
      <property name="Arrow Price/Stock" value="https://www.arrow.com/en/products/74lvc2g04gw-q100h/nexperia"/>
      <property name="Sheetname" value="Timing Circuit"/>
      <property name="Sheetfile" value="Timing_Circuit.kicad_sch"/>
      <sheetpath names="/Timing Circuit/" tstamps="/e95b1d8e-2e4e-4877-9121-2ee2965866b4/"/>
      <tstamps>eed48995-30c6-4618-956a-827dc9f923fc</tstamps>
    </comp>
    <comp ref="IC4">
      <value>LVC595</value>
      <footprint>SOIC127P600X175-16N</footprint>
      <datasheet>https://assets.nexperia.com/documents/data-sheet/74LVC595A.pdf</datasheet>
      <fields>
        <field name="Description">74LVC595A - 8-bit serial-in/serial-out or parallel-out shift register; 3-state@en-us</field>
        <field name="Height">1.75</field>
        <field name="Manufacturer_Name">Nexperia</field>
        <field name="Manufacturer_Part_Number">74LVC595AD,112</field>
        <field name="Mouser Part Number">771-74LVC595AD</field>
        <field name="Mouser Price/Stock">https://www.mouser.co.uk/ProductDetail/Nexperia/74LVC595AD112?qs=me8TqzrmIYV0b%2FEB25dYCQ%3D%3D</field>
      </fields>
      <libsource lib="Nexperia" part="74LVC595AD,112" description="74LVC595A - 8-bit serial-in/serial-out or parallel-out shift register; 3-state@en-us"/>
      <property name="Description" value="74LVC595A - 8-bit serial-in/serial-out or parallel-out shift register; 3-state@en-us"/>
      <property name="Height" value="1.75"/>
      <property name="Mouser Part Number" value="771-74LVC595AD"/>
      <property name="Mouser Price/Stock" value="https://www.mouser.co.uk/ProductDetail/Nexperia/74LVC595AD112?qs=me8TqzrmIYV0b%2FEB25dYCQ%3D%3D"/>
      <property name="Manufacturer_Name" value="Nexperia"/>
      <property name="Manufacturer_Part_Number" value="74LVC595AD,112"/>
      <property name="Sheetname" value="Timing Circuit"/>
      <property name="Sheetfile" value="Timing_Circuit.kicad_sch"/>
      <sheetpath names="/Timing Circuit/" tstamps="/e95b1d8e-2e4e-4877-9121-2ee2965866b4/"/>
      <tstamps>489fdbec-4328-4c47-9f64-efffa8afceea</tstamps>
    </comp>
    <comp ref="IC5">
      <value>LVC163</value>
      <footprint>SOP65P640X110-16N</footprint>
      <datasheet>https://assets.nexperia.com/documents/data-sheet/74LVC163.pdf</datasheet>
      <fields>
        <field name="Description">74LVC163 - Presettable synchronous 4-bit binary counter; synchronous reset@en-us</field>
        <field name="Height">1.1</field>
        <field name="Manufacturer_Name">Nexperia</field>
        <field name="Manufacturer_Part_Number">74LVC163PW,118</field>
        <field name="Mouser Part Number">771-74LVC163PW-T</field>
        <field name="Mouser Price/Stock">https://www.mouser.co.uk/ProductDetail/Nexperia/74LVC163PW118?qs=me8TqzrmIYUWRf9xrCNBjw%3D%3D</field>
      </fields>
      <libsource lib="Nexperia" part="74LVC163PW,118" description="74LVC163 - Presettable synchronous 4-bit binary counter; synchronous reset@en-us"/>
      <property name="Description" value="74LVC163 - Presettable synchronous 4-bit binary counter; synchronous reset@en-us"/>
      <property name="Height" value="1.1"/>
      <property name="Mouser Part Number" value="771-74LVC163PW-T"/>
      <property name="Mouser Price/Stock" value="https://www.mouser.co.uk/ProductDetail/Nexperia/74LVC163PW118?qs=me8TqzrmIYUWRf9xrCNBjw%3D%3D"/>
      <property name="Manufacturer_Name" value="Nexperia"/>
      <property name="Manufacturer_Part_Number" value="74LVC163PW,118"/>
      <property name="Sheetname" value="Timing Circuit"/>
      <property name="Sheetfile" value="Timing_Circuit.kicad_sch"/>
      <sheetpath names="/Timing Circuit/" tstamps="/e95b1d8e-2e4e-4877-9121-2ee2965866b4/"/>
      <tstamps>dc7160ec-8066-4129-b298-d1243e670f05</tstamps>
    </comp>
    <comp ref="IC6">
      <value>LVC139</value>
      <footprint>SOP65P640X110-16N</footprint>
      <datasheet>https://assets.nexperia.com/documents/data-sheet/74LVC139.pdf</datasheet>
      <fields>
        <field name="Description">74LVC139 - Dual 2-to-4 line decoder/demultiplexer@en-us</field>
        <field name="Height">1.1</field>
        <field name="Manufacturer_Name">Nexperia</field>
        <field name="Manufacturer_Part_Number">74LVC139PW,118</field>
        <field name="Mouser Part Number">771-74LVC139PW-T</field>
        <field name="Mouser Price/Stock">https://www.mouser.co.uk/ProductDetail/Nexperia/74LVC139PW118?qs=me8TqzrmIYVduxUT%2FTAZPg%3D%3D</field>
      </fields>
      <libsource lib="Nexperia" part="74LVC139PW,118" description="74LVC139 - Dual 2-to-4 line decoder/demultiplexer@en-us"/>
      <property name="Description" value="74LVC139 - Dual 2-to-4 line decoder/demultiplexer@en-us"/>
      <property name="Height" value="1.1"/>
      <property name="Mouser Part Number" value="771-74LVC139PW-T"/>
      <property name="Mouser Price/Stock" value="https://www.mouser.co.uk/ProductDetail/Nexperia/74LVC139PW118?qs=me8TqzrmIYVduxUT%2FTAZPg%3D%3D"/>
      <property name="Manufacturer_Name" value="Nexperia"/>
      <property name="Manufacturer_Part_Number" value="74LVC139PW,118"/>
      <property name="Sheetname" value="Timing Circuit"/>
      <property name="Sheetfile" value="Timing_Circuit.kicad_sch"/>
      <sheetpath names="/Timing Circuit/" tstamps="/e95b1d8e-2e4e-4877-9121-2ee2965866b4/"/>
      <tstamps>ac51870e-56b9-4651-a9e8-67e2cc5af78b</tstamps>
    </comp>
    <comp ref="IC7">
      <value>LVC574</value>
      <footprint>SOIC127P1032X265-20N</footprint>
      <datasheet>https://assets.nexperia.com/documents/data-sheet/74LVC574A.pdf</datasheet>
      <fields>
        <field name="Description">74LVC574A - Octal D-type flip-flop with 5 V tolerant inputs/outputs; positive edge-trigger (3-state)@en-us</field>
        <field name="Height">2.65</field>
        <field name="Manufacturer_Name">Nexperia</field>
        <field name="Manufacturer_Part_Number">74LVC574AD,118</field>
        <field name="Mouser Part Number">771-74LVC574AD-T</field>
        <field name="Mouser Price/Stock">https://www.mouser.co.uk/ProductDetail/Nexperia/74LVC574AD118?qs=me8TqzrmIYVVWemAtQ0oag%3D%3D</field>
      </fields>
      <libsource lib="Nexperia" part="74LVC574AD,118" description="74LVC574A - Octal D-type flip-flop with 5 V tolerant inputs/outputs; positive edge-trigger (3-state)@en-us"/>
      <property name="Description" value="74LVC574A - Octal D-type flip-flop with 5 V tolerant inputs/outputs; positive edge-trigger (3-state)@en-us"/>
      <property name="Height" value="2.65"/>
      <property name="Mouser Part Number" value="771-74LVC574AD-T"/>
      <property name="Mouser Price/Stock" value="https://www.mouser.co.uk/ProductDetail/Nexperia/74LVC574AD118?qs=me8TqzrmIYVVWemAtQ0oag%3D%3D"/>
      <property name="Manufacturer_Name" value="Nexperia"/>
      <property name="Manufacturer_Part_Number" value="74LVC574AD,118"/>
      <property name="Sheetname" value="Timing Circuit"/>
      <property name="Sheetfile" value="Timing_Circuit.kicad_sch"/>
      <sheetpath names="/Timing Circuit/" tstamps="/e95b1d8e-2e4e-4877-9121-2ee2965866b4/"/>
      <tstamps>87312563-a8bd-48eb-8def-3dc25db8c98f</tstamps>
    </comp>
    <comp ref="IC8">
      <value>LVC574</value>
      <footprint>SOIC127P1032X265-20N</footprint>
      <datasheet>https://assets.nexperia.com/documents/data-sheet/74LVC574A.pdf</datasheet>
      <fields>
        <field name="Description">74LVC574A - Octal D-type flip-flop with 5 V tolerant inputs/outputs; positive edge-trigger (3-state)@en-us</field>
        <field name="Height">2.65</field>
        <field name="Manufacturer_Name">Nexperia</field>
        <field name="Manufacturer_Part_Number">74LVC574AD,118</field>
        <field name="Mouser Part Number">771-74LVC574AD-T</field>
        <field name="Mouser Price/Stock">https://www.mouser.co.uk/ProductDetail/Nexperia/74LVC574AD118?qs=me8TqzrmIYVVWemAtQ0oag%3D%3D</field>
      </fields>
      <libsource lib="Nexperia" part="74LVC574AD,118" description="74LVC574A - Octal D-type flip-flop with 5 V tolerant inputs/outputs; positive edge-trigger (3-state)@en-us"/>
      <property name="Description" value="74LVC574A - Octal D-type flip-flop with 5 V tolerant inputs/outputs; positive edge-trigger (3-state)@en-us"/>
      <property name="Height" value="2.65"/>
      <property name="Mouser Part Number" value="771-74LVC574AD-T"/>
      <property name="Mouser Price/Stock" value="https://www.mouser.co.uk/ProductDetail/Nexperia/74LVC574AD118?qs=me8TqzrmIYVVWemAtQ0oag%3D%3D"/>
      <property name="Manufacturer_Name" value="Nexperia"/>
      <property name="Manufacturer_Part_Number" value="74LVC574AD,118"/>
      <property name="Sheetname" value="Timing Circuit"/>
      <property name="Sheetfile" value="Timing_Circuit.kicad_sch"/>
      <sheetpath names="/Timing Circuit/" tstamps="/e95b1d8e-2e4e-4877-9121-2ee2965866b4/"/>
      <tstamps>15188fd0-f3da-49d7-ba56-bd2b92d113d4</tstamps>
    </comp>
    <comp ref="J_Power1">
      <value>Conn_02x03</value>
      <footprint>Connector_PinSocket_2.54mm:PinSocket_2x03_P2.54mm_Vertical</footprint>
      <libsource lib="Connector_Generic" part="Conn_02x03_Odd_Even" description="Generic connector, double row, 02x03, odd/even pin numbering scheme (row 1 odd numbers, row 2 even numbers), script generated (kicad-library-utils/schlib/autogen/connector/)"/>
      <property name="Sheetname" value="Timing Circuit"/>
      <property name="Sheetfile" value="Timing_Circuit.kicad_sch"/>
      <sheetpath names="/Timing Circuit/" tstamps="/e95b1d8e-2e4e-4877-9121-2ee2965866b4/"/>
      <tstamps>ceb7857e-54fd-4b78-96d2-3b2d9c5cde4b</tstamps>
    </comp>
    <comp ref="J_Reset_Switch1">
      <value>Conn_01x02_Male</value>
      <footprint>Connector_PinHeader_2.54mm:PinHeader_1x02_P2.54mm_Vertical</footprint>
      <libsource lib="Connector" part="Conn_01x02_Male" description="Generic connector, single row, 01x02, script generated (kicad-library-utils/schlib/autogen/connector/)"/>
      <property name="Sheetname" value="Timing Circuit"/>
      <property name="Sheetfile" value="Timing_Circuit.kicad_sch"/>
      <sheetpath names="/Timing Circuit/" tstamps="/e95b1d8e-2e4e-4877-9121-2ee2965866b4/"/>
      <tstamps>4125929d-d482-4fc3-86ca-b336ddf3274b</tstamps>
    </comp>
    <comp ref="R1">
      <value>R</value>
      <footprint>Resistor_THT:R_Axial_DIN0204_L3.6mm_D1.6mm_P7.62mm_Horizontal</footprint>
      <libsource lib="Device" part="R" description="Resistor"/>
      <property name="Sheetname" value="Timing Circuit"/>
      <property name="Sheetfile" value="Timing_Circuit.kicad_sch"/>
      <sheetpath names="/Timing Circuit/" tstamps="/e95b1d8e-2e4e-4877-9121-2ee2965866b4/"/>
      <tstamps>56b4be7e-8210-4f35-b9f4-6ba59d377598</tstamps>
    </comp>
    <comp ref="X100Mhz1">
      <value>XLH735100.000000I</value>
      <footprint>XLH735100000000I</footprint>
      <datasheet>https://www.renesas.com/us/en/document/dst/xl-family-low-phase-noise-quartz-based-pll-oscillators-datasheet</datasheet>
      <fields>
        <field name="Description">SMD Crystal Oscillator 100MHz 3.3V 15pF 4-Pin CLCC Cut Tape</field>
        <field name="Height">1.45</field>
        <field name="Manufacturer_Name">Renesas Electronics</field>
        <field name="Manufacturer_Part_Number">XLH735100.000000I</field>
        <field name="Mouser Part Number">972-XLH735100000000I</field>
        <field name="Mouser Price/Stock">https://www.mouser.co.uk/ProductDetail/Renesas-IDT/XLH735100000000I?qs=itIaUkCn8qAdqSTL6ktHsw%3D%3D</field>
      </fields>
      <libsource lib="Renesas" part="XLH735100.000000I" description=""/>
      <property name="Description" value="SMD Crystal Oscillator 100MHz 3.3V 15pF 4-Pin CLCC Cut Tape"/>
      <property name="Height" value="1.45"/>
      <property name="Mouser Part Number" value="972-XLH735100000000I"/>
      <property name="Mouser Price/Stock" value="https://www.mouser.co.uk/ProductDetail/Renesas-IDT/XLH735100000000I?qs=itIaUkCn8qAdqSTL6ktHsw%3D%3D"/>
      <property name="Manufacturer_Name" value="Renesas Electronics"/>
      <property name="Manufacturer_Part_Number" value="XLH735100.000000I"/>
      <property name="Sheetname" value="Timing Circuit"/>
      <property name="Sheetfile" value="Timing_Circuit.kicad_sch"/>
      <sheetpath names="/Timing Circuit/" tstamps="/e95b1d8e-2e4e-4877-9121-2ee2965866b4/"/>
      <tstamps>e0b19861-0214-40f0-b1e3-c0f89ddf2a15</tstamps>
    </comp>
  </components>
  <libparts>
    <libpart lib="Connector" part="Conn_01x02_Male">
      <description>Generic connector, single row, 01x02, script generated (kicad-library-utils/schlib/autogen/connector/)</description>
      <docs>~</docs>
      <footprints>
        <fp>Connector*:*_1x??_*</fp>
      </footprints>
      <fields>
        <field name="Reference">J</field>
        <field name="Value">Conn_01x02_Male</field>
        <field name="Datasheet">~</field>
      </fields>
      <pins>
        <pin num="1" name="Pin_1" type="passive"/>
        <pin num="2" name="Pin_2" type="passive"/>
      </pins>
    </libpart>
    <libpart lib="Connector_Generic" part="Conn_02x03_Odd_Even">
      <description>Generic connector, double row, 02x03, odd/even pin numbering scheme (row 1 odd numbers, row 2 even numbers), script generated (kicad-library-utils/schlib/autogen/connector/)</description>
      <docs>~</docs>
      <footprints>
        <fp>Connector*:*_2x??_*</fp>
      </footprints>
      <fields>
        <field name="Reference">J</field>
        <field name="Value">Conn_02x03_Odd_Even</field>
        <field name="Datasheet">~</field>
      </fields>
      <pins>
        <pin num="1" name="Pin_1" type="passive"/>
        <pin num="2" name="Pin_2" type="passive"/>
        <pin num="3" name="Pin_3" type="passive"/>
        <pin num="4" name="Pin_4" type="passive"/>
        <pin num="5" name="Pin_5" type="passive"/>
        <pin num="6" name="Pin_6" type="passive"/>
      </pins>
    </libpart>
    <libpart lib="Device" part="CP">
      <footprints>
        <fp>CP_*</fp>
      </footprints>
      <fields>
        <field name="Reference">C</field>
        <field name="Value">Device_CP</field>
      </fields>
      <pins>
        <pin num="1" name="" type="passive"/>
        <pin num="2" name="" type="passive"/>
      </pins>
    </libpart>
    <libpart lib="Device" part="R">
      <description>Resistor</description>
      <docs>~</docs>
      <footprints>
        <fp>R_*</fp>
      </footprints>
      <fields>
        <field name="Reference">R</field>
        <field name="Value">R</field>
        <field name="Datasheet">~</field>
      </fields>
      <pins>
        <pin num="1" name="" type="passive"/>
        <pin num="2" name="" type="passive"/>
      </pins>
    </libpart>
    <libpart lib="Maxim" part="DS1813R-10+T&amp;R">
      <description>Maxim DS1813R-10+T&amp;R, Voltage Supervisor 4.25  4.49 V, Reset Input, 3-Pin SOT-23</description>
      <docs>https://componentsearchengine.com/Datasheets/2/DS1813R-10+T&amp;R.pdf</docs>
      <fields>
        <field name="Reference">IC</field>
        <field name="Value">DS1813R-10+T&amp;R</field>
        <field name="Footprint">SOT95P237X112-3N</field>
        <field name="Datasheet">https://componentsearchengine.com/Datasheets/2/DS1813R-10+T&amp;R.pdf</field>
        <field name="Description">Maxim DS1813R-10+T&amp;R, Voltage Supervisor 4.25  4.49 V, Reset Input, 3-Pin SOT-23</field>
        <field name="Height">1.12</field>
        <field name="Mouser Part Number">700-DS1813R-10T&amp;R</field>
        <field name="Mouser Price/Stock">https://www.mouser.co.uk/ProductDetail/Maxim-Integrated/DS1813R-10%2bTR?qs=0Y9aZN%252BMVCUEX%2FgvPX%252B6Nw%3D%3D</field>
        <field name="Manufacturer_Name">Maxim Integrated</field>
        <field name="Manufacturer_Part_Number">DS1813R-10+T&amp;R</field>
      </fields>
      <pins>
        <pin num="1" name="~{RST}" type="passive"/>
        <pin num="2" name="VCC" type="passive"/>
        <pin num="3" name="GND" type="passive"/>
      </pins>
    </libpart>
    <libpart lib="Nexperia" part="74LVC139PW,118">
      <description>74LVC139 - Dual 2-to-4 line decoder/demultiplexer@en-us</description>
      <docs>https://assets.nexperia.com/documents/data-sheet/74LVC139.pdf</docs>
      <fields>
        <field name="Reference">IC</field>
        <field name="Value">74LVC139PW,118</field>
        <field name="Footprint">SOP65P640X110-16N</field>
        <field name="Datasheet">https://assets.nexperia.com/documents/data-sheet/74LVC139.pdf</field>
        <field name="Description">74LVC139 - Dual 2-to-4 line decoder/demultiplexer@en-us</field>
        <field name="Height">1.1</field>
        <field name="Mouser Part Number">771-74LVC139PW-T</field>
        <field name="Mouser Price/Stock">https://www.mouser.co.uk/ProductDetail/Nexperia/74LVC139PW118?qs=me8TqzrmIYVduxUT%2FTAZPg%3D%3D</field>
        <field name="Manufacturer_Name">Nexperia</field>
        <field name="Manufacturer_Part_Number">74LVC139PW,118</field>
      </fields>
      <pins>
        <pin num="1" name="~{1E}" type="passive"/>
        <pin num="2" name="1A0" type="passive"/>
        <pin num="3" name="1A1" type="passive"/>
        <pin num="4" name="~{1Y0}" type="passive"/>
        <pin num="5" name="~{1Y1}" type="passive"/>
        <pin num="6" name="~{1Y2}" type="passive"/>
        <pin num="7" name="~{1Y3}" type="passive"/>
        <pin num="8" name="GND" type="passive"/>
        <pin num="9" name="~{2Y3}" type="passive"/>
        <pin num="10" name="~{2Y2}" type="passive"/>
        <pin num="11" name="~{2Y1}" type="passive"/>
        <pin num="12" name="~{2Y0}" type="passive"/>
        <pin num="13" name="2A1" type="passive"/>
        <pin num="14" name="2A0" type="passive"/>
        <pin num="15" name="~{2E}" type="passive"/>
        <pin num="16" name="VCC" type="passive"/>
      </pins>
    </libpart>
    <libpart lib="Nexperia" part="74LVC163PW,118">
      <description>74LVC163 - Presettable synchronous 4-bit binary counter; synchronous reset@en-us</description>
      <docs>https://assets.nexperia.com/documents/data-sheet/74LVC163.pdf</docs>
      <fields>
        <field name="Reference">IC</field>
        <field name="Value">74LVC163PW,118</field>
        <field name="Footprint">SOP65P640X110-16N</field>
        <field name="Datasheet">https://assets.nexperia.com/documents/data-sheet/74LVC163.pdf</field>
        <field name="Description">74LVC163 - Presettable synchronous 4-bit binary counter; synchronous reset@en-us</field>
        <field name="Height">1.1</field>
        <field name="Mouser Part Number">771-74LVC163PW-T</field>
        <field name="Mouser Price/Stock">https://www.mouser.co.uk/ProductDetail/Nexperia/74LVC163PW118?qs=me8TqzrmIYUWRf9xrCNBjw%3D%3D</field>
        <field name="Manufacturer_Name">Nexperia</field>
        <field name="Manufacturer_Part_Number">74LVC163PW,118</field>
      </fields>
      <pins>
        <pin num="1" name="~{MR}" type="passive"/>
        <pin num="2" name="CP" type="passive"/>
        <pin num="3" name="D0" type="passive"/>
        <pin num="4" name="D1" type="passive"/>
        <pin num="5" name="D2" type="passive"/>
        <pin num="6" name="D3" type="passive"/>
        <pin num="7" name="CEP" type="passive"/>
        <pin num="8" name="GND" type="passive"/>
        <pin num="9" name="~{PE}" type="passive"/>
        <pin num="10" name="CET" type="passive"/>
        <pin num="11" name="Q3" type="passive"/>
        <pin num="12" name="Q2" type="passive"/>
        <pin num="13" name="Q1" type="passive"/>
        <pin num="14" name="Q0" type="passive"/>
        <pin num="15" name="TC" type="passive"/>
        <pin num="16" name="VCC" type="passive"/>
      </pins>
    </libpart>
    <libpart lib="Nexperia" part="74LVC2G04GW-Q100H">
      <docs>https://assets.nexperia.com/documents/data-sheet/74LVC2G04_Q100.pdf</docs>
      <fields>
        <field name="Reference">IC</field>
        <field name="Value">74LVC2G04GW-Q100H</field>
        <field name="Footprint">SOP65P210X110-6N</field>
        <field name="Datasheet">https://assets.nexperia.com/documents/data-sheet/74LVC2G04_Q100.pdf</field>
        <field name="Description">74LVC2G04-Q100 - Dual inverter@en-us</field>
        <field name="Height">1.1</field>
        <field name="Manufacturer_Name">Nexperia</field>
        <field name="Manufacturer_Part_Number">74LVC2G04GW-Q100H</field>
        <field name="Mouser Part Number">771-74LVC2G04GWQ100H</field>
        <field name="Mouser Price/Stock">https://www.mouser.co.uk/ProductDetail/Nexperia/74LVC2G04GW-Q100H?qs=Yna0arPQ0CQTXbBDVSrZqQ%3D%3D</field>
        <field name="Arrow Part Number">74LVC2G04GW-Q100H</field>
        <field name="Arrow Price/Stock">https://www.arrow.com/en/products/74lvc2g04gw-q100h/nexperia</field>
      </fields>
      <pins>
        <pin num="1" name="1A" type="passive"/>
        <pin num="2" name="GND" type="passive"/>
        <pin num="3" name="2A" type="passive"/>
        <pin num="4" name="2Y" type="passive"/>
        <pin num="5" name="VCC" type="passive"/>
        <pin num="6" name="1Y" type="passive"/>
      </pins>
    </libpart>
    <libpart lib="Nexperia" part="74LVC574AD,118">
      <description>74LVC574A - Octal D-type flip-flop with 5 V tolerant inputs/outputs; positive edge-trigger (3-state)@en-us</description>
      <docs>https://assets.nexperia.com/documents/data-sheet/74LVC574A.pdf</docs>
      <fields>
        <field name="Reference">IC</field>
        <field name="Value">74LVC574AD,118</field>
        <field name="Footprint">SOIC127P1032X265-20N</field>
        <field name="Datasheet">https://assets.nexperia.com/documents/data-sheet/74LVC574A.pdf</field>
        <field name="Description">74LVC574A - Octal D-type flip-flop with 5 V tolerant inputs/outputs; positive edge-trigger (3-state)@en-us</field>
        <field name="Height">2.65</field>
        <field name="Mouser Part Number">771-74LVC574AD-T</field>
        <field name="Mouser Price/Stock">https://www.mouser.co.uk/ProductDetail/Nexperia/74LVC574AD118?qs=me8TqzrmIYVVWemAtQ0oag%3D%3D</field>
        <field name="Manufacturer_Name">Nexperia</field>
        <field name="Manufacturer_Part_Number">74LVC574AD,118</field>
      </fields>
      <pins>
        <pin num="1" name="~{OE}" type="passive"/>
        <pin num="2" name="D0" type="passive"/>
        <pin num="3" name="D1" type="passive"/>
        <pin num="4" name="D2" type="passive"/>
        <pin num="5" name="D3" type="passive"/>
        <pin num="6" name="D4" type="passive"/>
        <pin num="7" name="D5" type="passive"/>
        <pin num="8" name="D6" type="passive"/>
        <pin num="9" name="D7" type="passive"/>
        <pin num="10" name="GND" type="passive"/>
        <pin num="11" name="CP" type="passive"/>
        <pin num="12" name="Q7" type="passive"/>
        <pin num="13" name="Q6" type="passive"/>
        <pin num="14" name="Q5" type="passive"/>
        <pin num="15" name="Q4" type="passive"/>
        <pin num="16" name="Q3" type="passive"/>
        <pin num="17" name="Q2" type="passive"/>
        <pin num="18" name="Q1" type="passive"/>
        <pin num="19" name="Q0" type="passive"/>
        <pin num="20" name="VCC" type="passive"/>
      </pins>
    </libpart>
    <libpart lib="Nexperia" part="74LVC595AD,112">
      <description>74LVC595A - 8-bit serial-in/serial-out or parallel-out shift register; 3-state@en-us</description>
      <docs>https://assets.nexperia.com/documents/data-sheet/74LVC595A.pdf</docs>
      <fields>
        <field name="Reference">IC</field>
        <field name="Value">74LVC595AD,112</field>
        <field name="Footprint">SOIC127P600X175-16N</field>
        <field name="Datasheet">https://assets.nexperia.com/documents/data-sheet/74LVC595A.pdf</field>
        <field name="Description">74LVC595A - 8-bit serial-in/serial-out or parallel-out shift register; 3-state@en-us</field>
        <field name="Height">1.75</field>
        <field name="Mouser Part Number">771-74LVC595AD</field>
        <field name="Mouser Price/Stock">https://www.mouser.co.uk/ProductDetail/Nexperia/74LVC595AD112?qs=me8TqzrmIYV0b%2FEB25dYCQ%3D%3D</field>
        <field name="Manufacturer_Name">Nexperia</field>
        <field name="Manufacturer_Part_Number">74LVC595AD,112</field>
      </fields>
      <pins>
        <pin num="1" name="Q1" type="passive"/>
        <pin num="2" name="Q2" type="passive"/>
        <pin num="3" name="Q3" type="passive"/>
        <pin num="4" name="Q4" type="passive"/>
        <pin num="5" name="Q5" type="passive"/>
        <pin num="6" name="Q6" type="passive"/>
        <pin num="7" name="Q7" type="passive"/>
        <pin num="8" name="GND" type="passive"/>
        <pin num="9" name="Q7S" type="passive"/>
        <pin num="10" name="~{MR}" type="passive"/>
        <pin num="11" name="SHCP" type="passive"/>
        <pin num="12" name="STCP" type="passive"/>
        <pin num="13" name="~{OE}" type="passive"/>
        <pin num="14" name="DS" type="passive"/>
        <pin num="15" name="Q0" type="passive"/>
        <pin num="16" name="VCC" type="passive"/>
      </pins>
    </libpart>
    <libpart lib="Nexperia" part="74LVC74APW,118">
      <description>74LVC74A - Dual D-type flip-flop with set and reset; positive-edge trigger@en-us</description>
      <docs>https://assets.nexperia.com/documents/data-sheet/74LVC74A.pdf</docs>
      <fields>
        <field name="Reference">IC</field>
        <field name="Value">74LVC74APW,118</field>
        <field name="Footprint">SOP65P640X110-14N</field>
        <field name="Datasheet">https://assets.nexperia.com/documents/data-sheet/74LVC74A.pdf</field>
        <field name="Description">74LVC74A - Dual D-type flip-flop with set and reset; positive-edge trigger@en-us</field>
        <field name="Height">1.1</field>
        <field name="Mouser Part Number">771-74LVC74APW-T</field>
        <field name="Mouser Price/Stock">https://www.mouser.co.uk/ProductDetail/Nexperia/74LVC74APW118?qs=me8TqzrmIYVtXwVfet0lzw%3D%3D</field>
        <field name="Manufacturer_Name">Nexperia</field>
        <field name="Manufacturer_Part_Number">74LVC74APW,118</field>
      </fields>
      <pins>
        <pin num="1" name="~{1RD}" type="passive"/>
        <pin num="2" name="1D" type="passive"/>
        <pin num="3" name="1CP" type="passive"/>
        <pin num="4" name="~{1SD}" type="passive"/>
        <pin num="5" name="1Q" type="passive"/>
        <pin num="6" name="~{1Q}" type="passive"/>
        <pin num="7" name="GND" type="passive"/>
        <pin num="8" name="~{2Q}" type="passive"/>
        <pin num="9" name="2Q" type="passive"/>
        <pin num="10" name="~{2SD}" type="passive"/>
        <pin num="11" name="2CP" type="passive"/>
        <pin num="12" name="2D" type="passive"/>
        <pin num="13" name="~{2RD}" type="passive"/>
        <pin num="14" name="VCC" type="passive"/>
      </pins>
    </libpart>
    <libpart lib="Renesas" part="XLH735100.000000I">
      <docs>https://www.renesas.com/us/en/document/dst/xl-family-low-phase-noise-quartz-based-pll-oscillators-datasheet</docs>
      <fields>
        <field name="Reference">Y</field>
        <field name="Value">Renesas_XLH735100.000000I</field>
        <field name="Footprint">XLH735100000000I</field>
        <field name="Datasheet">https://www.renesas.com/us/en/document/dst/xl-family-low-phase-noise-quartz-based-pll-oscillators-datasheet</field>
        <field name="Description">SMD Crystal Oscillator 100MHz 3.3V 15pF 4-Pin CLCC Cut Tape</field>
        <field name="Height">1.45</field>
        <field name="Mouser Part Number">972-XLH735100000000I</field>
        <field name="Mouser Price/Stock">https://www.mouser.co.uk/ProductDetail/Renesas-IDT/XLH735100000000I?qs=itIaUkCn8qAdqSTL6ktHsw%3D%3D</field>
        <field name="Manufacturer_Name">Renesas Electronics</field>
        <field name="Manufacturer_Part_Number">XLH735100.000000I</field>
      </fields>
      <pins>
        <pin num="1" name="E/D" type="passive"/>
        <pin num="2" name="NC" type="no_connect"/>
        <pin num="3" name="GND" type="passive"/>
        <pin num="4" name="OUT" type="passive"/>
        <pin num="5" name="OUT2" type="passive"/>
        <pin num="6" name="VDD" type="passive"/>
      </pins>
    </libpart>
    <libpart lib="Wurth_Elektronik" part="885012207027">
      <description>Multilayer Ceramic Chip Capacitor WCAP-CSGP Series 0805 100pF X7R0805101K016DFCT10000</description>
      <docs>https://katalog.we-online.com/pbs/datasheet/885012207027.pdf</docs>
      <fields>
        <field name="Reference">C</field>
        <field name="Value">885012207027</field>
        <field name="Footprint">CAPC2012X90N</field>
        <field name="Datasheet">https://katalog.we-online.com/pbs/datasheet/885012207027.pdf</field>
        <field name="Description">Multilayer Ceramic Chip Capacitor WCAP-CSGP Series 0805 100pF X7R0805101K016DFCT10000</field>
        <field name="Height">0.9</field>
        <field name="Mouser Part Number">710-885012207027</field>
        <field name="Mouser Price/Stock">https://www.mouser.co.uk/ProductDetail/Wurth-Elektronik/885012207027?qs=0KOYDY2FL28IWYVDh0DkrQ%3D%3D</field>
        <field name="Manufacturer_Name">Wurth Elektronik</field>
        <field name="Manufacturer_Part_Number">885012207027</field>
      </fields>
      <pins>
        <pin num="1" name="" type="passive"/>
        <pin num="2" name="" type="passive"/>
      </pins>
    </libpart>
    <libpart lib="Wurth_Elektronik" part="885012207033">
      <description>Multilayer Ceramic Chip Capacitor WCAP-CSGP Series 0805 1000pF X7R0805102K016DFCT10000</description>
      <docs>https://katalog.we-online.com/pbs/datasheet/885012207033.pdf</docs>
      <fields>
        <field name="Reference">C</field>
        <field name="Value">885012207033</field>
        <field name="Footprint">CAPC2012X90N</field>
        <field name="Datasheet">https://katalog.we-online.com/pbs/datasheet/885012207033.pdf</field>
        <field name="Description">Multilayer Ceramic Chip Capacitor WCAP-CSGP Series 0805 1000pF X7R0805102K016DFCT10000</field>
        <field name="Height">0.9</field>
        <field name="Mouser Part Number">710-885012207033</field>
        <field name="Mouser Price/Stock">https://www.mouser.co.uk/ProductDetail/Wurth-Elektronik/885012207033?qs=0KOYDY2FL28ky2lrUPvQ%2Fw%3D%3D</field>
        <field name="Manufacturer_Name">Wurth Elektronik</field>
        <field name="Manufacturer_Part_Number">885012207033</field>
      </fields>
      <pins>
        <pin num="1" name="" type="passive"/>
        <pin num="2" name="" type="passive"/>
      </pins>
    </libpart>
  </libparts>
  <libraries>
    <library logical="Connector">
      <uri>C:\Program Files\KiCad\6.0\share\kicad\symbols\/Connector.kicad_sym</uri>
    </library>
    <library logical="Connector_Generic">
      <uri>C:\Program Files\KiCad\6.0\share\kicad\symbols\/Connector_Generic.kicad_sym</uri>
    </library>
    <library logical="Device">
      <uri>C:\Program Files\KiCad\6.0\share\kicad\symbols\/Device.kicad_sym</uri>
    </library>
    <library logical="Maxim">
      <uri>C:\Work\658-Computer\Kicad\Maxim.kicad_sym</uri>
    </library>
    <library logical="Nexperia">
      <uri>C:\Work\658-Computer\Kicad\Nexperia.kicad_sym</uri>
    </library>
    <library logical="Renesas">
      <uri>C:\Work\658-Computer\Kicad\Renesas.kicad_sym</uri>
    </library>
    <library logical="Wurth_Elektronik">
      <uri>C:\Work\658-Computer\Kicad\Wurth_Elektronik.kicad_sym</uri>
    </library>
  </libraries>
  <nets>
    <net code="1" name="/Timing Circuit/3.3V">
      <node ref="C1" pin="1" pintype="passive"/>
      <node ref="C10" pin="1" pintype="passive"/>
      <node ref="C11" pin="1" pintype="passive"/>
      <node ref="C12" pin="1" pintype="passive"/>
      <node ref="C3" pin="1" pintype="passive"/>
      <node ref="C4" pin="1" pintype="passive"/>
      <node ref="C5" pin="1" pintype="passive"/>
      <node ref="C6" pin="1" pintype="passive"/>
      <node ref="C7" pin="1" pintype="passive"/>
      <node ref="C8" pin="1" pintype="passive"/>
      <node ref="C9" pin="1" pintype="passive"/>
      <node ref="IC2" pin="14" pinfunction="VCC" pintype="passive"/>
      <node ref="IC3" pin="5" pinfunction="VCC" pintype="passive"/>
      <node ref="IC4" pin="16" pinfunction="VCC" pintype="passive"/>
      <node ref="IC5" pin="16" pinfunction="VCC" pintype="passive"/>
      <node ref="IC6" pin="16" pinfunction="VCC" pintype="passive"/>
      <node ref="IC7" pin="20" pinfunction="VCC" pintype="passive"/>
      <node ref="IC8" pin="20" pinfunction="VCC" pintype="passive"/>
      <node ref="J_Power1" pin="3" pinfunction="Pin_3" pintype="passive"/>
      <node ref="J_Power1" pin="4" pinfunction="Pin_4" pintype="passive"/>
      <node ref="X100Mhz1" pin="1" pinfunction="E/D" pintype="passive"/>
      <node ref="X100Mhz1" pin="6" pinfunction="VDD" pintype="passive"/>
    </net>
    <net code="2" name="/Timing Circuit/5V">
      <node ref="C2" pin="1" pintype="passive"/>
      <node ref="IC1" pin="2" pinfunction="VCC" pintype="passive"/>
      <node ref="J_Power1" pin="5" pinfunction="Pin_5" pintype="passive"/>
      <node ref="J_Power1" pin="6" pinfunction="Pin_6" pintype="passive"/>
    </net>
    <net code="3" name="/Timing Circuit/GND">
      <node ref="C1" pin="2" pintype="passive"/>
      <node ref="C10" pin="2" pintype="passive"/>
      <node ref="C11" pin="2" pintype="passive"/>
      <node ref="C12" pin="2" pintype="passive"/>
      <node ref="C2" pin="2" pintype="passive"/>
      <node ref="C3" pin="2" pintype="passive"/>
      <node ref="C4" pin="2" pintype="passive"/>
      <node ref="C5" pin="2" pintype="passive"/>
      <node ref="C6" pin="2" pintype="passive"/>
      <node ref="C7" pin="2" pintype="passive"/>
      <node ref="C8" pin="2" pintype="passive"/>
      <node ref="C9" pin="2" pintype="passive"/>
      <node ref="IC1" pin="3" pinfunction="GND" pintype="passive"/>
      <node ref="J_Power1" pin="1" pinfunction="Pin_1" pintype="passive"/>
      <node ref="J_Power1" pin="2" pinfunction="Pin_2" pintype="passive"/>
      <node ref="R1" pin="1" pintype="passive"/>
      <node ref="X100Mhz1" pin="3" pinfunction="GND" pintype="passive"/>
    </net>
    <net code="4" name="/Timing Circuit/RSTB">
      <node ref="IC1" pin="1" pinfunction="~{RST}" pintype="passive"/>
      <node ref="J_Reset_Switch1" pin="2" pinfunction="Pin_2" pintype="passive"/>
    </net>
    <net code="5" name="Net-(J_Reset_Switch1-Pad1)">
      <node ref="J_Reset_Switch1" pin="1" pinfunction="Pin_1" pintype="passive"/>
      <node ref="R1" pin="2" pintype="passive"/>
    </net>
    <net code="6" name="unconnected-(IC2-Pad1)">
      <node ref="IC2" pin="1" pinfunction="~{1RD}" pintype="passive"/>
    </net>
    <net code="7" name="unconnected-(IC2-Pad2)">
      <node ref="IC2" pin="2" pinfunction="1D" pintype="passive"/>
    </net>
    <net code="8" name="unconnected-(IC2-Pad3)">
      <node ref="IC2" pin="3" pinfunction="1CP" pintype="passive"/>
    </net>
    <net code="9" name="unconnected-(IC2-Pad4)">
      <node ref="IC2" pin="4" pinfunction="~{1SD}" pintype="passive"/>
    </net>
    <net code="10" name="unconnected-(IC2-Pad5)">
      <node ref="IC2" pin="5" pinfunction="1Q" pintype="passive"/>
    </net>
    <net code="11" name="unconnected-(IC2-Pad6)">
      <node ref="IC2" pin="6" pinfunction="~{1Q}" pintype="passive"/>
    </net>
    <net code="12" name="unconnected-(IC2-Pad7)">
      <node ref="IC2" pin="7" pinfunction="GND" pintype="passive"/>
    </net>
    <net code="13" name="unconnected-(IC2-Pad8)">
      <node ref="IC2" pin="8" pinfunction="~{2Q}" pintype="passive"/>
    </net>
    <net code="14" name="unconnected-(IC2-Pad9)">
      <node ref="IC2" pin="9" pinfunction="2Q" pintype="passive"/>
    </net>
    <net code="15" name="unconnected-(IC2-Pad10)">
      <node ref="IC2" pin="10" pinfunction="~{2SD}" pintype="passive"/>
    </net>
    <net code="16" name="unconnected-(IC2-Pad11)">
      <node ref="IC2" pin="11" pinfunction="2CP" pintype="passive"/>
    </net>
    <net code="17" name="unconnected-(IC2-Pad12)">
      <node ref="IC2" pin="12" pinfunction="2D" pintype="passive"/>
    </net>
    <net code="18" name="unconnected-(IC2-Pad13)">
      <node ref="IC2" pin="13" pinfunction="~{2RD}" pintype="passive"/>
    </net>
    <net code="19" name="unconnected-(IC3-Pad1)">
      <node ref="IC3" pin="1" pinfunction="1A" pintype="passive"/>
    </net>
    <net code="20" name="unconnected-(IC3-Pad2)">
      <node ref="IC3" pin="2" pinfunction="GND" pintype="passive"/>
    </net>
    <net code="21" name="unconnected-(IC3-Pad3)">
      <node ref="IC3" pin="3" pinfunction="2A" pintype="passive"/>
    </net>
    <net code="22" name="unconnected-(IC3-Pad4)">
      <node ref="IC3" pin="4" pinfunction="2Y" pintype="passive"/>
    </net>
    <net code="23" name="unconnected-(IC3-Pad6)">
      <node ref="IC3" pin="6" pinfunction="1Y" pintype="passive"/>
    </net>
    <net code="24" name="unconnected-(IC4-Pad1)">
      <node ref="IC4" pin="1" pinfunction="Q1" pintype="passive"/>
    </net>
    <net code="25" name="unconnected-(IC4-Pad2)">
      <node ref="IC4" pin="2" pinfunction="Q2" pintype="passive"/>
    </net>
    <net code="26" name="unconnected-(IC4-Pad3)">
      <node ref="IC4" pin="3" pinfunction="Q3" pintype="passive"/>
    </net>
    <net code="27" name="unconnected-(IC4-Pad4)">
      <node ref="IC4" pin="4" pinfunction="Q4" pintype="passive"/>
    </net>
    <net code="28" name="unconnected-(IC4-Pad5)">
      <node ref="IC4" pin="5" pinfunction="Q5" pintype="passive"/>
    </net>
    <net code="29" name="unconnected-(IC4-Pad6)">
      <node ref="IC4" pin="6" pinfunction="Q6" pintype="passive"/>
    </net>
    <net code="30" name="unconnected-(IC4-Pad7)">
      <node ref="IC4" pin="7" pinfunction="Q7" pintype="passive"/>
    </net>
    <net code="31" name="unconnected-(IC4-Pad8)">
      <node ref="IC4" pin="8" pinfunction="GND" pintype="passive"/>
    </net>
    <net code="32" name="unconnected-(IC4-Pad9)">
      <node ref="IC4" pin="9" pinfunction="Q7S" pintype="passive"/>
    </net>
    <net code="33" name="unconnected-(IC4-Pad10)">
      <node ref="IC4" pin="10" pinfunction="~{MR}" pintype="passive"/>
    </net>
    <net code="34" name="unconnected-(IC4-Pad11)">
      <node ref="IC4" pin="11" pinfunction="SHCP" pintype="passive"/>
    </net>
    <net code="35" name="unconnected-(IC4-Pad12)">
      <node ref="IC4" pin="12" pinfunction="STCP" pintype="passive"/>
    </net>
    <net code="36" name="unconnected-(IC4-Pad13)">
      <node ref="IC4" pin="13" pinfunction="~{OE}" pintype="passive"/>
    </net>
    <net code="37" name="unconnected-(IC4-Pad14)">
      <node ref="IC4" pin="14" pinfunction="DS" pintype="passive"/>
    </net>
    <net code="38" name="unconnected-(IC4-Pad15)">
      <node ref="IC4" pin="15" pinfunction="Q0" pintype="passive"/>
    </net>
    <net code="39" name="unconnected-(IC5-Pad1)">
      <node ref="IC5" pin="1" pinfunction="~{MR}" pintype="passive"/>
    </net>
    <net code="40" name="unconnected-(IC5-Pad2)">
      <node ref="IC5" pin="2" pinfunction="CP" pintype="passive"/>
    </net>
    <net code="41" name="unconnected-(IC5-Pad3)">
      <node ref="IC5" pin="3" pinfunction="D0" pintype="passive"/>
    </net>
    <net code="42" name="unconnected-(IC5-Pad4)">
      <node ref="IC5" pin="4" pinfunction="D1" pintype="passive"/>
    </net>
    <net code="43" name="unconnected-(IC5-Pad5)">
      <node ref="IC5" pin="5" pinfunction="D2" pintype="passive"/>
    </net>
    <net code="44" name="unconnected-(IC5-Pad6)">
      <node ref="IC5" pin="6" pinfunction="D3" pintype="passive"/>
    </net>
    <net code="45" name="unconnected-(IC5-Pad7)">
      <node ref="IC5" pin="7" pinfunction="CEP" pintype="passive"/>
    </net>
    <net code="46" name="unconnected-(IC5-Pad8)">
      <node ref="IC5" pin="8" pinfunction="GND" pintype="passive"/>
    </net>
    <net code="47" name="unconnected-(IC5-Pad9)">
      <node ref="IC5" pin="9" pinfunction="~{PE}" pintype="passive"/>
    </net>
    <net code="48" name="unconnected-(IC5-Pad10)">
      <node ref="IC5" pin="10" pinfunction="CET" pintype="passive"/>
    </net>
    <net code="49" name="unconnected-(IC5-Pad11)">
      <node ref="IC5" pin="11" pinfunction="Q3" pintype="passive"/>
    </net>
    <net code="50" name="unconnected-(IC5-Pad12)">
      <node ref="IC5" pin="12" pinfunction="Q2" pintype="passive"/>
    </net>
    <net code="51" name="unconnected-(IC5-Pad13)">
      <node ref="IC5" pin="13" pinfunction="Q1" pintype="passive"/>
    </net>
    <net code="52" name="unconnected-(IC5-Pad14)">
      <node ref="IC5" pin="14" pinfunction="Q0" pintype="passive"/>
    </net>
    <net code="53" name="unconnected-(IC5-Pad15)">
      <node ref="IC5" pin="15" pinfunction="TC" pintype="passive"/>
    </net>
    <net code="54" name="unconnected-(IC6-Pad1)">
      <node ref="IC6" pin="1" pinfunction="~{1E}" pintype="passive"/>
    </net>
    <net code="55" name="unconnected-(IC6-Pad2)">
      <node ref="IC6" pin="2" pinfunction="1A0" pintype="passive"/>
    </net>
    <net code="56" name="unconnected-(IC6-Pad3)">
      <node ref="IC6" pin="3" pinfunction="1A1" pintype="passive"/>
    </net>
    <net code="57" name="unconnected-(IC6-Pad4)">
      <node ref="IC6" pin="4" pinfunction="~{1Y0}" pintype="passive"/>
    </net>
    <net code="58" name="unconnected-(IC6-Pad5)">
      <node ref="IC6" pin="5" pinfunction="~{1Y1}" pintype="passive"/>
    </net>
    <net code="59" name="unconnected-(IC6-Pad6)">
      <node ref="IC6" pin="6" pinfunction="~{1Y2}" pintype="passive"/>
    </net>
    <net code="60" name="unconnected-(IC6-Pad7)">
      <node ref="IC6" pin="7" pinfunction="~{1Y3}" pintype="passive"/>
    </net>
    <net code="61" name="unconnected-(IC6-Pad8)">
      <node ref="IC6" pin="8" pinfunction="GND" pintype="passive"/>
    </net>
    <net code="62" name="unconnected-(IC6-Pad9)">
      <node ref="IC6" pin="9" pinfunction="~{2Y3}" pintype="passive"/>
    </net>
    <net code="63" name="unconnected-(IC6-Pad10)">
      <node ref="IC6" pin="10" pinfunction="~{2Y2}" pintype="passive"/>
    </net>
    <net code="64" name="unconnected-(IC6-Pad11)">
      <node ref="IC6" pin="11" pinfunction="~{2Y1}" pintype="passive"/>
    </net>
    <net code="65" name="unconnected-(IC6-Pad12)">
      <node ref="IC6" pin="12" pinfunction="~{2Y0}" pintype="passive"/>
    </net>
    <net code="66" name="unconnected-(IC6-Pad13)">
      <node ref="IC6" pin="13" pinfunction="2A1" pintype="passive"/>
    </net>
    <net code="67" name="unconnected-(IC6-Pad14)">
      <node ref="IC6" pin="14" pinfunction="2A0" pintype="passive"/>
    </net>
    <net code="68" name="unconnected-(IC6-Pad15)">
      <node ref="IC6" pin="15" pinfunction="~{2E}" pintype="passive"/>
    </net>
    <net code="69" name="unconnected-(IC7-Pad1)">
      <node ref="IC7" pin="1" pinfunction="~{OE}" pintype="passive"/>
    </net>
    <net code="70" name="unconnected-(IC7-Pad2)">
      <node ref="IC7" pin="2" pinfunction="D0" pintype="passive"/>
    </net>
    <net code="71" name="unconnected-(IC7-Pad3)">
      <node ref="IC7" pin="3" pinfunction="D1" pintype="passive"/>
    </net>
    <net code="72" name="unconnected-(IC7-Pad4)">
      <node ref="IC7" pin="4" pinfunction="D2" pintype="passive"/>
    </net>
    <net code="73" name="unconnected-(IC7-Pad5)">
      <node ref="IC7" pin="5" pinfunction="D3" pintype="passive"/>
    </net>
    <net code="74" name="unconnected-(IC7-Pad6)">
      <node ref="IC7" pin="6" pinfunction="D4" pintype="passive"/>
    </net>
    <net code="75" name="unconnected-(IC7-Pad7)">
      <node ref="IC7" pin="7" pinfunction="D5" pintype="passive"/>
    </net>
    <net code="76" name="unconnected-(IC7-Pad8)">
      <node ref="IC7" pin="8" pinfunction="D6" pintype="passive"/>
    </net>
    <net code="77" name="unconnected-(IC7-Pad9)">
      <node ref="IC7" pin="9" pinfunction="D7" pintype="passive"/>
    </net>
    <net code="78" name="unconnected-(IC7-Pad10)">
      <node ref="IC7" pin="10" pinfunction="GND" pintype="passive"/>
    </net>
    <net code="79" name="unconnected-(IC7-Pad11)">
      <node ref="IC7" pin="11" pinfunction="CP" pintype="passive"/>
    </net>
    <net code="80" name="unconnected-(IC7-Pad12)">
      <node ref="IC7" pin="12" pinfunction="Q7" pintype="passive"/>
    </net>
    <net code="81" name="unconnected-(IC7-Pad13)">
      <node ref="IC7" pin="13" pinfunction="Q6" pintype="passive"/>
    </net>
    <net code="82" name="unconnected-(IC7-Pad14)">
      <node ref="IC7" pin="14" pinfunction="Q5" pintype="passive"/>
    </net>
    <net code="83" name="unconnected-(IC7-Pad15)">
      <node ref="IC7" pin="15" pinfunction="Q4" pintype="passive"/>
    </net>
    <net code="84" name="unconnected-(IC7-Pad16)">
      <node ref="IC7" pin="16" pinfunction="Q3" pintype="passive"/>
    </net>
    <net code="85" name="unconnected-(IC7-Pad17)">
      <node ref="IC7" pin="17" pinfunction="Q2" pintype="passive"/>
    </net>
    <net code="86" name="unconnected-(IC7-Pad18)">
      <node ref="IC7" pin="18" pinfunction="Q1" pintype="passive"/>
    </net>
    <net code="87" name="unconnected-(IC7-Pad19)">
      <node ref="IC7" pin="19" pinfunction="Q0" pintype="passive"/>
    </net>
    <net code="88" name="unconnected-(IC8-Pad1)">
      <node ref="IC8" pin="1" pinfunction="~{OE}" pintype="passive"/>
    </net>
    <net code="89" name="unconnected-(IC8-Pad2)">
      <node ref="IC8" pin="2" pinfunction="D0" pintype="passive"/>
    </net>
    <net code="90" name="unconnected-(IC8-Pad3)">
      <node ref="IC8" pin="3" pinfunction="D1" pintype="passive"/>
    </net>
    <net code="91" name="unconnected-(IC8-Pad4)">
      <node ref="IC8" pin="4" pinfunction="D2" pintype="passive"/>
    </net>
    <net code="92" name="unconnected-(IC8-Pad5)">
      <node ref="IC8" pin="5" pinfunction="D3" pintype="passive"/>
    </net>
    <net code="93" name="unconnected-(IC8-Pad6)">
      <node ref="IC8" pin="6" pinfunction="D4" pintype="passive"/>
    </net>
    <net code="94" name="unconnected-(IC8-Pad7)">
      <node ref="IC8" pin="7" pinfunction="D5" pintype="passive"/>
    </net>
    <net code="95" name="unconnected-(IC8-Pad8)">
      <node ref="IC8" pin="8" pinfunction="D6" pintype="passive"/>
    </net>
    <net code="96" name="unconnected-(IC8-Pad9)">
      <node ref="IC8" pin="9" pinfunction="D7" pintype="passive"/>
    </net>
    <net code="97" name="unconnected-(IC8-Pad10)">
      <node ref="IC8" pin="10" pinfunction="GND" pintype="passive"/>
    </net>
    <net code="98" name="unconnected-(IC8-Pad11)">
      <node ref="IC8" pin="11" pinfunction="CP" pintype="passive"/>
    </net>
    <net code="99" name="unconnected-(IC8-Pad12)">
      <node ref="IC8" pin="12" pinfunction="Q7" pintype="passive"/>
    </net>
    <net code="100" name="unconnected-(IC8-Pad13)">
      <node ref="IC8" pin="13" pinfunction="Q6" pintype="passive"/>
    </net>
    <net code="101" name="unconnected-(IC8-Pad14)">
      <node ref="IC8" pin="14" pinfunction="Q5" pintype="passive"/>
    </net>
    <net code="102" name="unconnected-(IC8-Pad15)">
      <node ref="IC8" pin="15" pinfunction="Q4" pintype="passive"/>
    </net>
    <net code="103" name="unconnected-(IC8-Pad16)">
      <node ref="IC8" pin="16" pinfunction="Q3" pintype="passive"/>
    </net>
    <net code="104" name="unconnected-(IC8-Pad17)">
      <node ref="IC8" pin="17" pinfunction="Q2" pintype="passive"/>
    </net>
    <net code="105" name="unconnected-(IC8-Pad18)">
      <node ref="IC8" pin="18" pinfunction="Q1" pintype="passive"/>
    </net>
    <net code="106" name="unconnected-(IC8-Pad19)">
      <node ref="IC8" pin="19" pinfunction="Q0" pintype="passive"/>
    </net>
    <net code="107" name="unconnected-(X100Mhz1-Pad2)">
      <node ref="X100Mhz1" pin="2" pinfunction="NC" pintype="no_connect"/>
    </net>
    <net code="108" name="unconnected-(X100Mhz1-Pad4)">
      <node ref="X100Mhz1" pin="4" pinfunction="OUT" pintype="passive"/>
    </net>
    <net code="109" name="unconnected-(X100Mhz1-Pad5)">
      <node ref="X100Mhz1" pin="5" pinfunction="OUT2" pintype="passive+no_connect"/>
    </net>
  </nets>
</export>
